[{"stud_url": "https://www.fh-wedel.de/bewerben/bachelor/wirtschaftspsychologie/", "title": "Bachelor Angewandte Wirtschaftspsychologie | FH Wedel bei Hamburg", "paragraphs": ["n\u00e4chste digitale", "halbst\u00fcndigen zoompr\u00e4sentation", "studieninhalten", "infosessions", "masterstudieng\u00e4nge wirtschaftspsychologie", "wirtschaft menschliches verhalten aufeinandertreffen blick", "produkte markt", "rentieren integriertes", "auslandssemester f\u00fcrxaden internationalen bestens", "bachelorstudiumxaangewandte wirtschaftspsychologie", "naturwissenschaftliche informatik", "mathematik", "wirtschaftsbereich", "management marketing", "marketing", "servicemanagement", "siexaan", "organisation", "auslandssemesters", "workshops", "hochxaindemxaunternehmensvertreter vorlesungen", "einblicke berufsalltag", "berufliche kontaktexadies", "spannendexapraktikumspl\u00e4tze werkstudent", "attraktiven schreiben", "vielen hamburger gro\u00dfraum", "f\u00f6rderverein", "austausch", "wirtschaft", "diesexavertiefungsrichtung", "diesexavertiefungsrichtung", "studienverlauf", "praxisbl\u00f6cke vorlesungsphasen", "lernorte", "abxaw\u00e4hrend vorlesungszeit", "vollzeit", "pr\u00fcfungen vorlesungsfreien", "phasen", "theoretisches wissen", "schulen kompetenzen", "betriebliche abl\u00e4ufe", "praxiseins\u00e4tzen", "detaillierte dualen", "klima", "treten", "verbesserung", "insiderinfos", "berufspraxis", "wedeler hochschulbund zeichnet projektgruppen", "hochschulprozesse", "rechte", "daf\u00fcr verwendet auszuwerten", "eingaben eingegeben analysieren", "verwenden", "optimierungen", "llc", "erfassung", "benutzers", "nutzererlebnis", "drittanbieter", "client", "youtubenocookiecom", "buchstaben", "erm\u00f6glichen", "lokalen ger\u00e4t", "l\u00f6schen", "ausgelesen erm\u00f6glichen get\u00e4tigten", "besuchten ermitteln", "notwendige funktionsf\u00e4higkeit", "session", "analyse", "speichern", "besuche trafficquellen", "leistung", "n\u00fctzlichsten besucher", "navigieren fehlermeldungen", "l\u00e4ngeren ger\u00e4t", "gesammelten verbessern", "benutzerfreundlichkeit", "intuitivere navigation", "positiveres", "bachelor angewandte wirtschaftspsychologie fh wedel bei hamburg"]}, {"stud_url": "https://www.fh-wedel.de/bewerben/bachelor/betriebswirtschaftslehre/", "title": "Bachelor BWL | FH Wedel bei Hamburg", "paragraphs": ["n\u00e4chste digitale", "halbst\u00fcndigen zoompr\u00e4sentation", "studieninhalten", "infosessions", "masterstudieng\u00e4nge", "wirtschaftliche zusammenh\u00e4nge", "bwlstudium richtige imxabachelorstudiengangxabetriebswirtschaftslehre", "lernen betriebe", "abl\u00e4ufe", "wertsch\u00f6pfung wertefluss controlling", "branche", "grundkenntnisse informatik", "datenauswertung", "aktueller", "projekte", "einstieg", "orientieren", "sch\u00e4rfen berufliches bereichen", "marketing dienstleistungsmanagement rechnungs", "besondere bwlstudium", "dasxaf\u00fcnftexasemester integrierten auslandssemesters chile s\u00fcdafrika", "siebten sammeln", "praktikums", "auslandserfahrung", "karriere", "drittanbietercookies", "solide grundlagen", "finanzwirtschaft", "statistik mathematik", "einf\u00fchrende veranstaltungen", "besucht entscheiden wahl", "dienstleistungsmanagement", "accounting", "auditing", "marketing", "medien", "skills vervollst\u00e4ndigen stundenplan", "pr\u00e4sentationstechniken", "kurse", "f\u00fcnfte integriertes", "auslandssemester monaten", "erfahrung", "gro\u00dfer praxisbezug", "notwendige r\u00fcstzeug", "berufsalltag", "namhafte metropolregion", "kontakt", "besonderes", "betriebspraktikums", "wirtschaftswissenschaftlichen fragestellung", "vertiefungsrichtung", "bachelor", "science bsc vertiefungsrichtung", "f\u00e4higkeiten", "rechnungslegung", "accounting", "auditing internationale rechnungslegung", "konzernrechnungslegung", "unternehmensbesteuerung", "job", "praxisbezug", "schnellen einstieg", "praktika werkstudentent\u00e4tigkeiten", "kooperationspartner lehrveranstaltungen", "bed\u00fcrfnisse", "w\u00fcnsche pr\u00e4ferenzen", "marketing", "marktorientierte unternehmensf\u00fchrung zentrum", "vertiefungsrichtung", "technologischen gesellschaftlichen wandel", "weiterer fokus", "neuen medien", "bedeutung marketing", "marketing medien", "marketing", "praktischer fallbeispiele dieserxavertiefungsrichtung", "wirtschaftliche entwicklung", "letzten jahrzehnte", "weltweit komplexe globale unternehmensnetzwerke g\u00fcterstromsysteme", "effizient lenken gestalten", "betriebs", "gesichtspunkten", "fundierte kenntnisse f\u00e4higkeiten", "beschaffung", "produktion logistik", "schwerpunktthemen", "produktions", "vertiefungsrichtung", "dienstleistungsmanagement", "unterschiedlicher dienstleistungsfeldern", "treibende kr\u00e4fte digitalisierung wirtschaft", "unternehmensf\u00fchrung", "marketing", "produktion vertiefungsrichtung", "spezifisch weiterentwickelt befassen servicestrategien", "dienstleistungsqualit\u00e4t", "serviceprozess", "erfolgreiches dienstleistungscontrolling", "f\u00fcnften m\u00f6glichkeit", "reale problemstellungen", "aufgabe projekt", "durchzuf\u00fchren", "projekt", "pr\u00e4sentation", "ergebnisbericht j\u00fcngsten bwl sieben dual", "praxisbl\u00f6cke vorlesungsphasen", "lernorte", "abxaw\u00e4hrend vorlesungszeit", "vollzeit", "pr\u00fcfungen vorlesungsfreien", "phasen", "theoretisches wissen", "schulen kompetenzen", "betriebliche abl\u00e4ufe", "praxiseins\u00e4tzen", "detaillierte dualen", "duales", "dynamische", "f\u00fchrungskr\u00e4fte", "rund prozent", "erhalt abschlusszeugnisse arbeitsvertrag", "wirtschaftspr\u00fcfungsgesellschaft oderxagro\u00dfen unternehmensberatung", "marketingmanager", "hersteller", "karriere", "internationalen erfahrung", "praxisorientierten beste jobchancen", "internationalen konzernen", "institutionen", "besch\u00e4ftigungen dienstleistungssektor", "etwa banken", "industrie", "logistik", "neuen gesch\u00e4ftsideen", "eigenexa", "gr\u00fcnden", "workshops", "prozess professoren", "jungunternehmern", "rat", "bachelorabschluss", "masterstudium", "f\u00fchrungspositionen qualifizieren", "klima", "treten", "verbesserung", "insiderinfos", "berufspraxis", "wedeler hochschulbund zeichnet projektgruppen", "hochschulprozesse", "rechte", "daf\u00fcr verwendet auszuwerten", "eingaben eingegeben analysieren", "verwenden", "optimierungen", "llc", "erfassung", "benutzers", "nutzererlebnis", "drittanbieter", "client", "youtubenocookiecom", "buchstaben", "erm\u00f6glichen", "lokalen ger\u00e4t", "l\u00f6schen", "ausgelesen erm\u00f6glichen get\u00e4tigten", "besuchten ermitteln", "notwendige funktionsf\u00e4higkeit", "session", "analyse", "speichern", "besuche trafficquellen", "leistung", "n\u00fctzlichsten besucher", "navigieren fehlermeldungen", "l\u00e4ngeren ger\u00e4t", "gesammelten verbessern", "benutzerfreundlichkeit", "intuitivere navigation", "positiveres", "bachelor bwl fh wedel bei hamburg"]}, {"stud_url": "https://www.fh-wedel.de/bewerben/bachelor/", "title": "Bachelor-Studieng\u00e4nge in IT, Technik & Wirtschaft | FH Wedel", "paragraphs": ["metropolregion", "zw\u00f6lf bachelorstudieng\u00e4nge wirtschaft", "technik", "informatik", "abschlussarbeit", "berufsleben", "fallstudien", "fr\u00fch problemstellungen unternehmensalltag", "wertvolle praxiserfahrung", "regelm\u00e4\u00dfig eingebunden", "insights", "branche", "w\u00f6chigen", "gegenzug", "vorlesungsphasen", "dauern", "n\u00f6tigen veranstaltungen", "mehr m\u00f6glichkeit", "studieng\u00e4ngen", "betriebswirtschaftslehre wirtschaftsingenieurwesen", "auslandssemester integriert", "office", "bachelorstudiengang", "bachelorstudiengang", "studienformen", "bachelorstudiengang computer", "games", "technology", "bachelorstudiengang", "intelligence", "ecommerce", "informatik", "bachelorstudiengang itmanagement consulting auditing", "bachelorstudiengang", "technische informatik", "wirtschaftsinformatik", "bachelorstudiengang", "rechte", "eingaben eingegeben analysieren", "verwenden", "optimierungen", "llc", "erfassung", "benutzers", "nutzererlebnis", "drittanbieter", "client", "youtubenocookiecom", "buchstaben", "erm\u00f6glichen", "lokalen ger\u00e4t", "l\u00f6schen", "ausgelesen erm\u00f6glichen get\u00e4tigten", "besuchten ermitteln", "notwendige funktionsf\u00e4higkeit", "session", "analyse", "speichern", "besuche trafficquellen", "leistung", "n\u00fctzlichsten besucher", "navigieren fehlermeldungen", "l\u00e4ngeren ger\u00e4t", "gesammelten verbessern", "benutzerfreundlichkeit", "intuitivere navigation", "positiveres", "bachelorstudieng\u00e4nge in it technik wirtschaft fh wedel"]}, {"stud_url": "https://www.fh-wedel.de/bewerben/bachelor/data-science-artificial-intelligence/", "title": "Bachelor Data Science & Artificial Intelligence | FH Wedel bei Hamburg", "paragraphs": ["n\u00e4chste digitale", "halbst\u00fcndigen zoompr\u00e4sentation", "studieninhalten", "infosessions", "spezialisierung", "scientist", "liegenden grund", "strategisch entscheidend kunden", "produkt serviceangebot", "analyse", "datenquellen", "verschiedener unternehmensbereiche fachgebiete", "t\u00e4tigkeit", "stark interdisziplin\u00e4r", "bachelorstudiengangxadata science", "intelligence", "praxisrelevanz", "stiftungspartner projekte", "realer", "datenbeispiele", "interdisziplin\u00e4rer wirtschaft", "sodass unmittelbar m\u00f6gliche einsatzbereiche kennenlernen", "teamarbeit sozialkompetenz", "erm\u00f6glichen praktischen", "\u00fcbungen", "informatik", "wirtschaft", "guten lernerfolg", "bereiche informatik", "statistik", "kerndisziplinen fundiertes methodenwissen", "potenziale datenquellen", "analyseverfahren datenhaltungskonzepte", "analysieren", "verfahren", "k\u00fcnstlichen intelligenz", "machine learnings", "l\u00f6sen video", "drittanbietercookies", "science", "intelligence", "einordnung", "betriebswirtschaftliche zusammenh\u00e4nge", "software", "erarbeiten mathematischen wirtschaftswissenschaftlichen grundlagen", "ebenso grundlegende programmierkenntnisse", "lehrveranstaltungen stundenplan", "explizit", "anteil", "studiengangsspezifischen inhalte data engineering", "fundament data", "scientist", "artificial", "intelligenter methoden", "konventionelle techniken", "machine", "hohen stellenwert", "effiziente analyse", "hochdimensionaler w\u00e4hlen vertiefungsrichtung", "kompetenzen", "vertiefung ecommerce industrie", "informatik", "operations management marketing services", "gesammeltes wissen", "umfangreichen projektarbeit", "science", "betriebspraktikums", "bachelor", "science bsc", "data", "ecommerce", "kunden", "erfassung onlineangebote besonders nahe liegend verst\u00e4ndnis", "gesch\u00e4ftsprozesse ecommerce", "grundlagen", "tiefer gehende webanalyse", "datengetriebenen steuerung", "unmittelbare ankn\u00fcpfungspunkt", "data scientists", "vertiefungsrichtung", "ausgebildeter data", "scientist", "gro\u00dfes knowhow", "informatik", "unterscheiden f\u00e4higkeiten", "softwareentwicklers softwareentwickler wesentlich umfangreichere kenntnisse", "betrachtung informatik", "vertiefungsrichtung", "tiefer gehende kenntnisse informatik", "vertiefungsrichtung", "technische grundlagen", "digitalisierungsprozess", "wichtiges bet\u00e4tigungsfeld", "data", "diagnose produktionssysteme", "industrie", "herausforderungen", "realenxawelt vertiefungsrichtung", "wirtschaft", "komplexe globale unternehmensnetzwerke g\u00fcterstromsysteme", "gestalten", "betriebs", "gesichtspunkten", "fundierte kenntnisse", "produktion", "logistik", "schwerpunktthemen", "operative strategische produktionsmanagement", "bed\u00fcrfnisse", "w\u00fcnsche pr\u00e4ferenzen", "marketing", "marktorientierte unternehmensf\u00fchrung zentrum", "vertiefungsrichtung", "rasante technologische gesellschaftliche wandel", "marketing einschneidende ver\u00e4nderungen entwicklungen", "blickwinkel", "science", "l\u00f6sungsm\u00f6glichkeiten fachgebiet", "human resources", "erschlie\u00dfen marken", "praktischer fallbeispiele dieserxavertiefungsrichtung", "science", "artificial", "intelligence sieben dual", "studienverlauf", "praxisbl\u00f6cke vorlesungsphasen", "lernorte", "abxaw\u00e4hrend vorlesungszeit", "vollzeit", "pr\u00fcfungen vorlesungsfreien", "phasen", "theoretisches wissen", "schulen kompetenzen", "betriebliche abl\u00e4ufe", "praxiseins\u00e4tzen", "detaillierte dualen", "duales", "mehr bauen", "zunehmend k\u00fcnstliche intelligenz", "onlineshopping", "industriellen fertigung", "anwendung", "chatbots", "k\u00fcnstlicher intelligenz", "einsatzbereiche data", "scientists", "k\u00fcnstlicher intelligenz", "desto differenzierter gesuchten berufsbilder", "unmittelbar bachelorstudiengangxadata science", "intelligence", "zukunftsgewandten", "datengetriebener probleml\u00f6ser", "unterschiedlichen bereichen", "medizinforschung", "marketing qualit\u00e4tsmanagement produzierender", "data", "scientists", "relevante entscheidungsgrundlage", "wertsch\u00f6pfungsprozess", "data", "analyst", "datenauswertung", "prognostizierung datenvisualisierung", "engineer", "software", "f\u00e4higkeiten", "verantwortung", "betrieb eingesetzten artificial intelligence infrastruktur", "neuen gesch\u00e4ftsideen", "eigenexastartups", "gr\u00fcnden", "workshops", "prozess professoren", "jungunternehmern", "rat", "bachelorabschluss", "f\u00fchrungsaufgaben wissenschaftliche karriere", "masterstudiengang wissensmanagement", "klima", "treten", "verbesserung", "insiderinfos", "berufspraxis", "rechte", "vorbehalten", "daf\u00fcr verwendet auszuwerten", "eingaben eingegeben analysieren", "verwenden", "optimierungen", "llc", "erfassung", "benutzers", "nutzererlebnis", "drittanbieter", "client", "youtubenocookiecom", "buchstaben", "erm\u00f6glichen", "lokalen ger\u00e4t", "l\u00f6schen", "ausgelesen erm\u00f6glichen get\u00e4tigten", "besuchten ermitteln", "notwendige funktionsf\u00e4higkeit", "session", "analyse", "speichern", "besuche trafficquellen", "leistung", "n\u00fctzlichsten besucher", "navigieren fehlermeldungen", "l\u00e4ngeren ger\u00e4t", "gesammelten verbessern", "benutzerfreundlichkeit", "intuitivere navigation", "positiveres", "bachelor data science artificial intelligence fh wedel bei hamburg"]}, {"stud_url": "https://www.fh-wedel.de/bewerben/bachelor/e-commerce/", "title": "Bachelor E-Commerce | FH Wedel bei Hamburg", "paragraphs": ["n\u00e4chste digitale", "halbst\u00fcndigen zoompr\u00e4sentation", "studieninhalten", "infosessions", "masterstudieng\u00e4nge", "otto group", "siebensemestrigen", "bachelor", "fachlich aufeinander aufbauen bekleidung", "lebensmittel", "versicherungen videostreaming sogar anspruchsvolle dienstleistungen inzwischen internet", "digitales marketing", "onlinehandel", "online", "buchung", "bachelorstudiengang", "ecommerce", "mix speziellen ecommercef\u00e4chern", "wahl informatik", "wirtschaft", "fokus", "vermehrt technischen funktionsweisen", "ecommerce", "besch\u00e4ftigen technischen aufbau", "onlineshops servicefunktionen produktsuche empfehlungsmechanismus", "erarbeiten themen suchmaschinenoptimierung", "kaufendenxamit", "praxistest", "reale gesch\u00e4ftsidee passendes onlineshopsystem", "jahr", "webshop justizvollzugsanstalt", "studentisches projekt", "forschung", "trends", "austausch", "interessante kontakte", "kn\u00fcpfen", "zahlreichen kooperationspartnern", "siexapraktika", "video", "drittanbietercookies", "bachelorstudium ecommerce", "spezielle ecommerce webanalytics digital marketing retailing", "verbindung physischen gesch\u00e4ften", "grundlagen", "programmierung", "diskrete mathematik", "statistik operations research mathematische planungsrechnung", "wahl vertiefungsrichtung", "informationstechnischen betriebswirtschaftlichen rahmen", "freiwilligen auslandssemesters", "betriebspraktikums", "spezielle software", "zugreifenxabeispielsweise", "gute infrastruktur", "forschung gebiet", "eye", "bachelor", "science bsc", "informatik", "technische grundlage", "digitalen interaktion", "ecommerce", "zusammenh\u00e4nge", "sp\u00e4tere arbeit", "ecommerce", "vertiefungsrichtung", "informatik", "programmierkenntnisse", "intensiv programmstrukturenxaalgorithmen", "themen anwendung", "k\u00fcnstlicher intelligenz", "t\u00e4tigkeiten", "besonderes knowhow marketing projektmanagement", "vertiefungsrichtung", "wirtschaft fokus", "betriebswirtschaftliche themen", "marketing", "controlling", "stundenplan m\u00e4rkte", "ressourcen", "investition finanzierung", "marketing", "medienmanagement ecommerce", "sieben dual", "praxisbl\u00f6cke vorlesungsphasen", "lernorte", "abxaw\u00e4hrend vorlesungszeit", "vollzeit", "pr\u00fcfungen vorlesungsfreien", "phasen", "theoretisches wissen", "schulen kompetenzen", "betriebliche abl\u00e4ufe", "praxiseins\u00e4tzen", "detaillierte dualen", "verantwortlich duales bachelorabsolventinnen", "dynamische", "f\u00fchrungskr\u00e4fte", "rund prozent", "erhalt", "abschlusszeugnisse arbeitsvertrag", "schnittstellenkompetenz", "informatik", "marketing", "gute karriereperspektiven", "webanalyst", "digitalen marketing", "karriere", "praxisorientierten", "offen bachelorabsolventinnen abolventen", "schnittstelle softwareentwicklung marketing", "systemkomponenten", "webanalysten", "webentwickler", "onlineproduktmanager", "projektmanager", "omnichannelmarketing", "neuen gesch\u00e4ftsideen", "startups", "workshops", "prozess professoren", "jungunternehmerinnen unternhemern", "rat bachelorabschluss", "masterstudium", "absolventinnen schlie\u00dfen", "f\u00fchrungspositionen qualifizieren", "klima", "treten", "verbesserung", "insiderinfos", "berufspraxis", "wedeler hochschulbund zeichnet projektgruppen", "hochschulprozesse", "rechte", "daf\u00fcr verwendet auszuwerten", "eingaben eingegeben analysieren", "verwenden", "optimierungen", "llc", "erfassung", "benutzers", "nutzererlebnis", "drittanbieter", "client", "youtubenocookiecom", "buchstaben", "erm\u00f6glichen", "lokalen ger\u00e4t", "l\u00f6schen", "ausgelesen erm\u00f6glichen get\u00e4tigten", "besuchten ermitteln", "notwendige funktionsf\u00e4higkeit", "session", "analyse", "speichern", "besuche trafficquellen", "leistung", "n\u00fctzlichsten besucher", "navigieren fehlermeldungen", "l\u00e4ngeren ger\u00e4t", "gesammelten verbessern", "benutzerfreundlichkeit", "intuitivere navigation", "positiveres", "bachelor ecommerce fh wedel bei hamburg"]}, {"stud_url": "https://www.fh-wedel.de/bewerben/bachelor/computer-games-technology/", "title": "Bachelor Computer Games Technology  | FH Wedel bei Hamburg", "paragraphs": ["n\u00e4chste digitale", "halbst\u00fcndigen zoompr\u00e4sentation", "studieninhalten", "infosessions", "computerspiele", "derxabachelorstudiengang computer", "games", "technology", "computerspiele programmieren", "realit\u00e4tsnahe virtuelle welten", "grundlagen", "informatik", "technik computeranimation virtual reality special effects", "stundenplan ort", "moderne infrastruktur", "verf\u00fcgung", "intensiv virtueller realit\u00e4t", "programmieren", "inhalte langj\u00e4hrige erfahrung fachbereichs", "spieleindustrie", "gro\u00dfes professionelles netzwerk", "gamesexpertenxasorgen", "anwenden xabeispielsweise", "forschungs", "entwicklungsaufgabenxahier", "namhaften", "wirtschaft", "metropolregion st\u00e4rkt video", "drittanbietercookies", "computer", "games", "computerspielen stecken", "grafik virtuelle realit\u00e4ten", "virtuelle intensiver erlebbar programmieren software", "stundenplan", "special effects", "interaktive geometrische modellierung", "gamedesign unix shellprogrammierung", "simulationen", "objekte", "studienschwerpunkte", "computergrafik", "menschmaschineninteraktion k\u00fcnstliche intelligenz", "basis", "technischer informatik", "mathematik", "zeitgem\u00e4\u00dfe infrastruktur", "verf\u00fcgung arbeitspl\u00e4tze", "aktuellster software", "video audiostudiosxa", "lichttechnik", "greenbox", "mischpulten gamerpcs", "neuester grafikhardware", "gameinterfaces", "cobench", "cave", "begehbarer kubus", "w\u00e4nde projektionssystemen", "benutzer", "spezielle brille", "virtuelle eingebettet", "cobench", "gro\u00dfer interaktionstisch", "mehrere cobench", "besondere finanzieller unterst\u00fctzung", "eigenes", "betriebspraktikums", "bachelor", "science bsc", "computer", "games", "studienverlauf", "praxisbl\u00f6cke vorlesungsphasen", "lernorte", "abxaw\u00e4hrend vorlesungszeit", "vollzeit", "pr\u00fcfungen vorlesungsfreien", "phasen", "theoretisches wissen", "schulen kompetenzen", "betriebliche abl\u00e4ufe", "praxiseins\u00e4tzen", "detaillierte dualen", "duales", "dynamische", "f\u00fchrungskr\u00e4fte", "rund prozent", "erhalt", "abschlusszeugnisse arbeitsvertrag", "hochschulabg\u00e4nger computer", "games", "spieleindustrie", "\u00fcberall realit\u00e4tsnahe welten", "anspruchsvolle grafiken", "sounds", "sogenannte serious", "chirurgen interaktiven", "komplizierte operationen", "flugzeugindustrie", "wunder einsatzbereiche", "itunternehmen spezialisierungen", "visualisierung werbe filmbranche autoindustrie", "architektur", "komplexe spielewelten", "gameproduktmanager", "koordiniert optimiert", "informatikkenntnisse", "mobile", "developer mobile betriebssysteme", "smartphones tablets", "optimiert neuen gesch\u00e4ftsideen", "startups", "workshops", "prozess professoren", "jungunternehmern", "rat", "bachelorabschluss", "f\u00fchrungsaufgaben wissenschaftliche arbeiten", "klima", "treten", "verbesserung", "trainingssimulation", "insiderinfos", "berufspraxis", "rechte", "vorbehalten", "daf\u00fcr verwendet auszuwerten", "eingaben eingegeben analysieren", "verwenden", "optimierungen", "llc", "erfassung", "benutzers", "nutzererlebnis", "drittanbieter", "client", "youtubenocookiecom", "buchstaben", "erm\u00f6glichen", "lokalen ger\u00e4t", "l\u00f6schen", "ausgelesen erm\u00f6glichen get\u00e4tigten", "besuchten ermitteln", "notwendige funktionsf\u00e4higkeit", "session", "analyse", "speichern", "besuche trafficquellen", "leistung", "n\u00fctzlichsten besucher", "navigieren fehlermeldungen", "l\u00e4ngeren ger\u00e4t", "gesammelten verbessern", "benutzerfreundlichkeit", "intuitivere navigation", "positiveres", "bachelor computer games technology fh wedel bei hamburg"]}, {"stud_url": "https://www.fh-wedel.de/bewerben/bachelor/it-ingenieurwesen/", "title": "Bachelor IT-Ingenieurwesen | FH Wedel bei Hamburg", "paragraphs": ["n\u00e4chste digitale", "halbst\u00fcndigen zoompr\u00e4sentation", "studieninhalten", "infosessions", "masterstudieng\u00e4nge digitalisierung", "f\u00fchrtxadazu technischen disziplinen mehr fachkr\u00e4fte", "itkenntnissen", "hamburgxadenxabachelorstudiengang itingenieurwesen leben", "gerufen beidesxakombiniert klassisches ingenieurwesen", "informatikxastudierende", "grund", "systeme", "digitalen wirtschaft", "weise", "istxadie produktion", "modernster informationstechnik", "verzahntxadie jobchancen", "besser digitale transformation", "werdenxaingenieure", "itkenntnissen", "technik", "naturwissenschaft", "informatikxaim", "individuelle schwerpunkte wahl", "energiesysteme informatik", "elektronik", "berufseinstieg", "vorzubereiten fundierte praktischexaerfahrung", "wesentliche bestandteile", "erfolgreichen karriereweg", "unternehmensvertreter rahmen", "vorlesungen seminaren fallstudien", "diskutieren", "fachwissen", "sowiexain forschungs", "beixafirmen erfolgreichxazusammenarbeiten video", "drittanbietercookies", "bachelorstudiums", "naturxaund", "ingenieurwissenschaftliche grundlagen", "klassische informatikausbildung", "allgemeines interesse naturwissenschaft", "technik", "stundenplan mathematik", "physik", "chemie digitaltechnik", "programmierung", "anwendungenxader", "studienbeginn", "vertiefungsrichtung", "m\u00f6glichkeit", "individuelle studienschwerpunkte", "setzenxasie", "informatik", "elektronik", "energiesysteme umfangreiche projekte", "kommunikationsf\u00e4higkeit", "gen\u00fcgend handwerkszeug", "werkstudent", "betriebspraktikum vorlesungsfreien", "absolvierenxaim rahmen", "freiwilligen auslandssemesters", "bildet bachelorarbeit", "praktikum", "erfolgreichen studienabschluss", "bachelor", "science bsc", "energiesysteme bekommen m\u00f6glichkeit", "energiewende aktiv mitzugestalten", "energetischen grundlagen energie", "umwelttechnik", "projektbezogen smart grid", "verfahrenstechnik", "vertiefungsrichtung", "informatik", "kenntnisse softwareentwicklung", "inhalten webanwendungen softwarequalit\u00e4t", "beispiel", "java", "halbleiter anwendungsbereiche elektronik", "grundlegenden eigenschaften", "linearer elektrischer", "systematisch entwurfs", "elektronischer schaltungen", "herangef\u00fchrt", "gebiet echtzeitsysteme", "einerseits methoden mechanismen", "systeme", "konkurrierenden", "hardwaretechnische echtzeitbetrieb", "unterschiede echtzeitbetriebssystem vergleich", "itingenieurwesen", "sieben dual", "praxisbl\u00f6cke vorlesungsphasen", "lernorte", "abxaw\u00e4hrend vorlesungszeit", "vollzeit", "pr\u00fcfungen vorlesungsfreien", "phasen", "theoretisches wissen", "schulen kompetenzen", "betriebliche abl\u00e4ufe", "praxiseins\u00e4tzen", "detaillierte dualen", "duales", "technik", "digitalisierung", "jobs", "technik einsatzgebiete vielf\u00e4ltig itingenieure arbeit", "raumfahrttechnik", "medizintechnik elektroindustrie", "maschinen", "rechnernetze", "anwendungen", "datenstr\u00f6me", "entwicklung", "informatikanteil", "hoch studienabg\u00e4nger problemlos itbereich unterkommen klassisches einsatzgebiet", "ingenieure informatiker", "norddeutschen luftfahrtbranche firmen", "zulieferer", "beratungsgesellschaften medizintechnik", "energietechnik itingenieure gebraucht", "einsatzgebiet digitale fertigung", "industrie", "produzierenden betriebe", "norddeutschen suche", "ingenieuren", "itkenntnissen", "dynamische", "f\u00fchrungskr\u00e4fte", "rund prozent", "erhalt", "abschlusszeugnisse arbeitsvertrag", "neuen gesch\u00e4ftsideen", "unterst\u00fctzt eigenexastartups", "workshops", "prozess professoren", "jungunternehmern", "rat", "entweder beruf", "masterstudiengang", "ingenieur", "f\u00fchrungspositionen qualifizieren", "itengineeringxaaber", "klima", "treten", "verbesserung", "insiderinfos", "berufspraxis", "rechte", "vorbehalten", "daf\u00fcr verwendet auszuwerten", "eingaben eingegeben analysieren", "verwenden", "optimierungen", "llc", "erfassung", "benutzers", "nutzererlebnis", "drittanbieter", "client", "youtubenocookiecom", "buchstaben", "erm\u00f6glichen", "lokalen ger\u00e4t", "l\u00f6schen", "ausgelesen erm\u00f6glichen get\u00e4tigten", "besuchten ermitteln", "notwendige funktionsf\u00e4higkeit", "session", "analyse", "speichern", "besuche trafficquellen", "leistung", "n\u00fctzlichsten besucher", "navigieren fehlermeldungen", "l\u00e4ngeren ger\u00e4t", "gesammelten verbessern", "benutzerfreundlichkeit", "intuitivere navigation", "positiveres", "bachelor itingenieurwesen fh wedel bei hamburg"]}, {"stud_url": "https://www.fh-wedel.de/bewerben/bachelor/it-management-consulting-auditing/", "title": "Bachelor IT-Management, Consulting & Auditing | FH Wedel bei Hamburg", "paragraphs": ["n\u00e4chste digitale", "halbst\u00fcndigen zoompr\u00e4sentation", "studieninhalten", "infosessions", "unternehmensprozesse zugeh\u00f6rige itsystemexaimmer komplexer", "experten", "solides betriebswirtschaftliches wissen", "damitxaitl\u00f6sungen erarbeiten", "itsysteme", "korrekt durchf\u00fchren", "bachelorstudiengang", "itmanagement consulting auditing", "grundlagen informatik", "wirtschaft", "spektrum", "einzigartig hochschullandschaft", "qualifiziertem", "jahr", "initiative", "wirtschaft", "praxisvertretern", "praxisrelevant", "start", "vertretern", "folgender starke praxisbezug", "vorlesungen", "seminarexaoder fallstudien", "reale vorxaberichten berufsalltag", "regen", "wissenstransfer wirtschaft", "umfassenden projekten", "konkreten aufgabenstellungen knowhow", "vertiefungsrichtung kontext", "lern", "arbeitsatmosph\u00e4re kontakt", "video", "drittanbietercookies", "bachelorstudiengangs", "consulting auditing", "informationssysteme", "werdenxastudieninhalte informatik bwl itmanagement", "vergleich", "studieng\u00e4ngen", "wirtschaftsinformatik", "itgest\u00fctztexagesch\u00e4ftsprozesse", "\u00e4u\u00dfere risiken", "itsicherheit", "f\u00fchrungs", "gro\u00dfe itmanagement leistung", "itsysteme", "optimal bedarf", "mathematik betriebswirtschaftslehre finanzwirtschaft", "diskrete mathematik", "stundenplanxaab", "softwaregestaltung accounting", "auditing", "fokus", "gestaltung", "software rechnungs", "handwerkszeug", "werkstudent", "betriebspraktikum vorlesungsfreien", "absolvierenxaim rahmen", "freiwilligen auslandssemesters", "bildet bachelorarbeit", "praktikum", "studienabschluss", "bachelor", "science bsc vertiefungsrichtung", "softwaregestaltung", "itsicherheit softwaredesign", "softwarequalit\u00e4t", "prozessmodellierung", "reine programmierung", "software angriffe", "datendiebstahl", "softwaredesign", "softwaresysteme", "lernen ma\u00dfnahmen qualit\u00e4tssicherung", "software", "prozesse", "veranstaltung", "prozessmodellierung", "techniken", "vertiefungsrichtung", "f\u00e4higkeiten", "rechnungslegung", "accounting", "auditing internationale rechnungslegung", "konzernrechnungslegung", "unternehmensbesteuerung", "job", "praxisbezug", "schnellen einstieg", "praktika werkstudentent\u00e4tigkeiten", "ausgew\u00e4hlte kooperationspartner lehrveranstaltungen", "integriert vertiefungsrichtung", "itmanagement consulting auditing sieben dual", "studienverlauf", "praxisbl\u00f6cke vorlesungsphasen", "lernorte", "abxaw\u00e4hrend vorlesungszeit", "vollzeit", "pr\u00fcfungen vorlesungsfreien", "phasen", "theoretisches wissen", "schulen kompetenzen", "betriebliche abl\u00e4ufe", "praxiseins\u00e4tzen", "detaillierte dualen", "verantwortlich duales", "vielen fehlen schl\u00fcsselpositionen", "itsystemenxadie n\u00f6tigen experten", "berufsanf\u00e4nger job", "l\u00fccke", "bachelorstudiengangs", "consulting auditing", "m\u00f6glichkeit", "unmittelbar abschlussxaherausfordernde spannenden branche", "knowhow", "undxainformatik", "wirtschaftliche prozesse", "geeignete itsysteme", "etablierenxabeispielsweise", "itsysteme", "dassxadie unternehmenszielexaerreicht konzipieren", "ma\u00dfgeschneiderte softwarel\u00f6sungen", "leiter", "itressourcen zugeh\u00f6rigen budgets", "steuernxaunsere genie\u00dfen", "hervorragenden ruf", "dynamische", "f\u00fchrungskr\u00e4fte", "absolventenstatistik", "rund prozent", "bachelorabsolventen", "erhalt", "abschlusszeugnisse arbeitsvertrag", "neuen gesch\u00e4ftsideen", "eigenexastartups", "gr\u00fcnden", "workshops", "prozess professoren", "jungunternehmern", "rat", "bachelorabschluss", "f\u00fchrungsaufgaben wissenschaftliche karriere", "masterstudiengang wissensmanagement", "klima", "treten", "verbesserung", "insiderinfos", "berufspraxis", "rechte", "vorbehalten", "daf\u00fcr verwendet auszuwerten", "eingaben eingegeben analysieren", "verwenden", "optimierungen", "llc", "erfassung", "benutzers", "nutzererlebnis", "drittanbieter", "client", "youtubenocookiecom", "buchstaben", "erm\u00f6glichen", "lokalen ger\u00e4t", "l\u00f6schen", "ausgelesen erm\u00f6glichen get\u00e4tigten", "besuchten ermitteln", "notwendige funktionsf\u00e4higkeit", "session", "analyse", "speichern", "besuche trafficquellen", "leistung", "n\u00fctzlichsten besucher", "navigieren fehlermeldungen", "l\u00e4ngeren ger\u00e4t", "gesammelten verbessern", "benutzerfreundlichkeit", "intuitivere navigation", "positiveres", "bachelor itmanagement consulting auditing fh wedel bei hamburg"]}, {"stud_url": "https://www.fh-wedel.de/bewerben/bachelor/informatik/", "title": "Bachelor Informatik | FH Wedel bei Hamburg", "paragraphs": ["n\u00e4chste digitale", "halbst\u00fcndigen zoompr\u00e4sentation", "studieninhalten", "infosessions", "unterschiedlichste zwecke", "autos", "haushaltsger\u00e4te", "bachelorstudiums", "programmieren", "siexadaf\u00fcr", "studienschwerpunkt", "wichtigsten programmiersprachen konzepte", "z\u00fcgig aneignen softwareentwicklung", "programmcode", "passende datenmodelle", "optimale verarbeitungslogik", "entwicklungsprozess", "gro\u00dfen daraufxaihr", "praxisnah", "optimal anforderungen", "vorzubereiten unternehmensvertretern", "seminaren fallstudien", "fr\u00fchxain forschungs", "profitieren kooperationsnetzwerkxader", "wirtschaft", "konzept", "absolventenstatistik", "bachelorabsolventenxain", "au\u00dferordentlich begehrt jobchancen", "video", "drittanbietercookies", "schwerpunkt informatikstudiums", "softwareprogrammierung", "industrie\u00fcblichen programmiersprachen java c", "systeme", "programmieren", "php java script", "angewandter informatik", "besonderer", "mathematik", "mitbringen", "informatikstudium gro\u00dfe diskrete mathematik", "lineare", "informations", "bestandteile wirtschaftliche grundlagen", "berufsleben", "themen", "datenschutz", "enterpriseressourcesysteme", "gruppenarbeit gro\u00dfgeschrieben", "kommilitonen", "gro\u00dfen softwareprojekten gruppen", "teilaufgaben", "zusammengesetzt ausreichendes handwerkszeug", "werkstudent", "betriebspraktikum vorlesungsfreien", "absolvierenxaim rahmen", "freiwilligen auslandssemesters", "betriebspraktikums", "bachelor", "science bsc", "studienverlauf", "praxisbl\u00f6cke vorlesungsphasen", "lernorte", "abxaw\u00e4hrend vorlesungszeit", "vollzeit", "pr\u00fcfungen vorlesungsfreien", "phasen", "theoretisches wissen", "schulen kompetenzen", "betriebliche abl\u00e4ufe", "praxiseins\u00e4tzen", "detaillierte dualen", "duales", "hoch engagierte dynamische fach", "erhalt", "abschlusszeugnisse arbeitsvertrag", "informatik", "informatiker", "absolventenzahlen", "aktuellen bedarf", "arbeit", "informationstechnik", "softwareh\u00e4usern", "maschinenbau", "medizin", "programmieren software", "unternehmensberatung", "neuen gesch\u00e4ftsideen", "eigenexastartups", "workshops", "prozess professoren", "jungunternehmern", "rat", "entweder beruf", "f\u00fchrungspositionen qualifizieren", "eignet wissensmanagement", "klima", "treten", "verbesserung", "insiderinfos", "berufspraxis", "rechte", "vorbehalten", "daf\u00fcr verwendet auszuwerten", "eingaben eingegeben analysieren", "verwenden", "optimierungen", "llc", "erfassung", "benutzers", "nutzererlebnis", "drittanbieter", "client", "youtubenocookiecom", "buchstaben", "erm\u00f6glichen", "lokalen ger\u00e4t", "l\u00f6schen", "ausgelesen erm\u00f6glichen get\u00e4tigten", "besuchten ermitteln", "notwendige funktionsf\u00e4higkeit", "session", "analyse", "speichern", "besuche trafficquellen", "leistung", "n\u00fctzlichsten besucher", "navigieren fehlermeldungen", "l\u00e4ngeren ger\u00e4t", "gesammelten verbessern", "benutzerfreundlichkeit", "intuitivere navigation", "positiveres", "bachelor informatik fh wedel bei hamburg"]}, {"stud_url": "https://www.fh-wedel.de/bewerben/bachelor/medieninformatik/", "title": "Bachelor Medieninformatik | FH Wedel bei Hamburg", "paragraphs": ["n\u00e4chste digitale", "halbst\u00fcndigen zoompr\u00e4sentation", "studieninhalten", "infosessions", "tonxaimmer", "realit\u00e4tsnahe virtuelle weltenxamedieninformatiker", "multimedialen inhalte", "entsprechende software", "entwickeln alsxateilbereich klassischen informatik", "diexamedieninformatik", "beides", "medien", "informationstechnik", "stundenplan", "audio videobearbeitung", "fachlich kompetent auszubilden anforderungen", "projekte", "spielexadie infrastruktur", "einenxaregieraum", "umgang", "cut", "berufsrelevantexalehrinhalte diexahochschule", "kooperiert lernen m\u00f6glichkeit", "praktikums", "bachelorarbeit", "kontakt", "lern", "arbeitsatmosph\u00e4re video", "drittanbietercookies", "derxabachelorstudiengangxamedieninformatik", "f\u00e4chern", "computergrafik", "mathematik", "naturwissenschaftlichen f\u00e4chern", "informatik", "video", "kurse themen", "marketing", "datenschutz", "soft", "computerprogrammen", "illustrator indesign", "auseinanderxain", "software computeranimationen film", "videoplanung dreh", "moderne infrastruktur", "video audiostudio", "sechsxaquadratmeter gro\u00dfen computerbilder", "dbrille virtuelle welt", "durchs weltall", "gravitationsboden sorgtxaf\u00fcr", "realit\u00e4tsnahes stimulierendes", "ausreichendes handwerkszeug", "betriebspraktika vorlesungsfreien", "freiwilligen auslandssemesters", "bildet bachelorarbeit", "praktikum", "erfolgreichen studienabschluss", "bachelor", "science bsc", "studienverlauf", "praxisbl\u00f6cke vorlesungsphasen", "lernorte", "abxaw\u00e4hrend vorlesungszeit", "vollzeit", "pr\u00fcfungen vorlesungsfreien", "phasen", "theoretisches wissen", "schulen kompetenzen", "betriebliche abl\u00e4ufe", "praxiseins\u00e4tzen", "detaillierte dualen", "duales", "hoch engagierte mitarbeiter", "rund prozent", "arbeitsvertrag", "fach\u00fcbergreifendes", "medieninformatiker", "h\u00e4ufig softwareentwickler multimedia", "animation", "multimediaprodukte", "entstehen", "nutzerfreundliche shopsysteme", "programmieren interaktive undxaanimierte", "apps", "smartphones tablets", "verlage archive \u00f6ffentliche einrichtungen", "interaktive multimediale informationssysteme", "software", "filmproduktionen k\u00fcmmern", "medieninformatiker komplexe", "multimediale zusatzinformationen film", "fernsehbranche arbeiten postproduktion", "dfilmwelten", "startups", "workshops", "prozess professoren", "jungunternehmern", "rat", "entweder beruf", "f\u00fchrungspositionen qualifizieren", "schwerpunkt", "medien wissensmanagement", "klima", "treten", "verbesserung", "insiderinfos", "berufspraxis", "rechte", "vorbehalten", "daf\u00fcr verwendet auszuwerten", "eingaben eingegeben analysieren", "verwenden", "optimierungen", "llc", "erfassung", "benutzers", "nutzererlebnis", "drittanbieter", "client", "youtubenocookiecom", "buchstaben", "erm\u00f6glichen", "lokalen ger\u00e4t", "l\u00f6schen", "ausgelesen erm\u00f6glichen get\u00e4tigten", "besuchten ermitteln", "notwendige funktionsf\u00e4higkeit", "session", "analyse", "speichern", "besuche trafficquellen", "leistung", "n\u00fctzlichsten besucher", "navigieren fehlermeldungen", "l\u00e4ngeren ger\u00e4t", "gesammelten verbessern", "benutzerfreundlichkeit", "intuitivere navigation", "positiveres", "bachelor medieninformatik fh wedel bei hamburg"]}, {"stud_url": "https://www.fh-wedel.de/bewerben/bachelor/smart-technology/", "title": "Bachelor Smart Technology | FH Wedel bei Hamburg", "paragraphs": ["n\u00e4chste digitale", "halbst\u00fcndigen zoompr\u00e4sentation", "studieninhalten", "infosessions", "zweifel", "digitalisierung", "alltagsgegenst\u00e4nde fahrzeuge", "mehr smarte ger\u00e4te verdr\u00e4ngtxaum", "entwicklung", "gutxaausgebildete", "technik", "undxaarbeiten", "imxastudiengang smart technology", "intelligente systeme", "entwerfen", "projektorientiertes lernen", "hilfestellungen", "projektumsetzung", "l\u00f6sung aufgabenstellung", "projektorientierte", "kreativit\u00e4tstechniken", "projekt prototyp", "smarten", "aspekte", "energiequelle", "laufe", "projektarbeit", "gr\u00f6\u00dferen gr\u00f6\u00dferen smart technology projekt", "interdisziplin\u00e4r konkreten aufgabenstellungen", "realer kunden design thinking", "prozess", "ausstattung", "projektarbeit", "t\u00fcftlerlabor", "reale projekte", "umxaum", "prototypen werkzeuge laserschneider", "ddrucker verf\u00fcgung", "einenxaprojektraum", "arbeitspl\u00e4tzen", "intelligente ger\u00e4te", "denxasmartroom", "nachbildung", "showroom", "projekte inspirationshilfe", "spezialisieren", "robotik informatik", "grafik", "science", "vertiefungsrichtungen wahl", "praktikums erfahrung", "kontakt", "anregenden", "arbeitsatmosph\u00e4re unternehmensvertreter", "sorgen", "berufsrelevante", "wertvolle einblicke", "realit\u00e4ten", "karriere", "drittanbietercookies", "natur", "ingenieurwissenxadschaftliche grundlagen", "lehrveranstaltungen", "technik", "elektronik", "ausgebaut diskrete mathematik", "\u00fcbertragungstechnik", "stundenplan", "intrapreneurship", "m\u00f6glichkeit", "kompetenzen", "mitzugestalten wahl technik", "robotik informatik", "grafik", "fokus", "mechanik", "hardware konzentrieren", "vertiefungsrichtungen informatik", "grafik", "science", "spezieller software programmierung", "besonderer fokus", "ambient assisted living smart", "\u00e4ltere beeintr\u00e4chtigte menschen", "denkbar herde", "abschalten beleuchtung", "smartphone", "begriff smart", "systeme", "hausversorgung", "unterhaltungselektronik", "rahmen freiwilligen", "auslandssemesters", "sammelnxadas", "betriebspraktikum", "berufserfahrung", "bachelor", "science bsc vertiefungsrichtung", "computergrafik", "bildbearbeitung", "\u00fcberblick", "zugeh\u00f6rige \u00fcbung", "struktur", "digitaler bilddaten", "digitale bilder", "darstellen anpassen", "befassen komposition filterung", "analyse", "c", "bildbearbeitung analyse", "objektorientierte programmierung", "k\u00fcnstliche intelligenz", "itsicherheit", "schwerpunkte vertiefungsrichtung", "grundlagen", "fortgeschrittenen", "beispiel java", "technologien", "k\u00fcnstlichen intelligenz", "itsicherheit", "sicherheit", "softwaresystemen", "software", "sicherheitsaspekten", "bedrohungs angriffsarten ma\u00dfnahmen", "echtzeitsysteme robotik", "bildbearbeitung analyse", "schwerpunkte", "echtzeitsysteme", "entwerfen", "software hardwarekonzepten auseinander programmieren software", "eingebettete systeme", "parallele prozesse", "techniken", "modellierung", "industrieroboter intelligente sensoren", "digitale bilder", "analysieren filtern", "praktischen \u00fcbungen", "erlernte", "systemtheorie", "regelungs", "grundlegenden konzepte", "funktionaltransformationen befassen zielen", "regelungstechnik", "stabilit\u00e4t dynamik", "offener geschlossener regelkreise", "passende", "numerik", "numerische l\u00f6sungen", "methoden", "vertiefungsrichtung", "smarten verarbeitung", "sensoren smarten", "gro\u00dfe menge", "gute entscheidungen", "vorhersagen", "statistik", "konkreter verarbeitung", "analyse", "smart", "sieben dual", "studienverlauf", "praxisbl\u00f6cke vorlesungsphasen", "lernorte", "abxaw\u00e4hrend vorlesungszeit", "vollzeit", "pr\u00fcfungen vorlesungsfreien", "phasen", "theoretisches wissen", "schulen kompetenzen", "betriebliche abl\u00e4ufe", "praxiseins\u00e4tzen", "detaillierte dualen", "duales", "studienabg\u00e4nger genie\u00dfen hervorragenden ruf", "zuverl\u00e4ssige engagierte", "statistik", "bachelor", "erhalt", "arbeitsvertrag", "praxisnahen f\u00e4cher\u00fcbergreifenden offen", "berater dabei unterst\u00fctzen smarte produkte", "t\u00e4tigkeit", "ingenieuren", "kompetenzen", "hardware", "software", "bachelorabschluss", "masterstudium", "itengineering", "technik", "qualifizieren", "neuen gesch\u00e4ftsideen", "startups", "workshops", "prozess professoren", "jungunternehmern", "rat", "klima", "treten", "verbesserung", "insiderinfos", "berufspraxis", "wedeler hochschulbund zeichnet projektgruppen", "hochschulprozesse", "rechte", "daf\u00fcr verwendet auszuwerten", "eingaben eingegeben analysieren", "verwenden", "optimierungen", "llc", "erfassung", "benutzers", "nutzererlebnis", "drittanbieter", "client", "youtubenocookiecom", "buchstaben", "erm\u00f6glichen", "lokalen ger\u00e4t", "l\u00f6schen", "ausgelesen erm\u00f6glichen get\u00e4tigten", "besuchten ermitteln", "notwendige funktionsf\u00e4higkeit", "session", "analyse", "speichern", "besuche trafficquellen", "leistung", "n\u00fctzlichsten besucher", "navigieren fehlermeldungen", "l\u00e4ngeren ger\u00e4t", "gesammelten verbessern", "benutzerfreundlichkeit", "intuitivere navigation", "positiveres", "bachelor smart technology fh wedel bei hamburg"]}, {"stud_url": "https://www.fh-wedel.de/bewerben/bachelor/wirtschaftsingenieurwesen/", "title": "Bachelor Wirtschaftsingenieurwesen | FH Wedel bei Hamburg", "paragraphs": ["n\u00e4chste digitale", "halbst\u00fcndigen zoompr\u00e4sentation", "studieninhalten", "infosessions", "masterstudieng\u00e4nge wirtschaftsingenieure", "technik wirtschaft", "rentieren integriertes", "auslandssemester f\u00fcrxaden internationalen bestens", "bachelorstudium", "naturwissenschaftliche materialtechnik", "verfahrens", "wirtschaftsbereich", "controlling management marketing", "wirtschaft", "f\u00fcnfte siexaan", "organisation", "auslandssemesters", "workshops", "hochxaindemxaunternehmensvertreter vorlesungen", "einblicke berufsalltag", "berufliche kontaktexadies", "spannendexapraktikumspl\u00e4tze werkstudent", "attraktiven schreiben", "austausch", "wirtschaft", "video", "drittanbietercookies", "wirtschaftsingenieure", "gef\u00e4chertes f\u00e4cher\u00fcbergreifende ausrichtung", "ganz unterschiedlichen themen technik", "informatik", "grundlagen mathematik", "physik", "chemie", "studienbeginn", "ua", "grundlagen produktionswirtschaft", "unternehmensf\u00fchrung", "verfahrenstechnik", "spezialisieren", "f\u00fcnf schwerpunkte", "informationsmanagement", "elektro", "informationstechnik", "marketing", "industrie", "management", "auslandserfahrung", "integrierte auslandssemester praxisorientierte", "guten kontakte", "jobeinstieg", "handwerkszeug", "werkstudentent\u00e4tigkeit", "siebten arbeiten betriebspraktikums", "berufserfahrung", "bachelor", "science bsc", "welten", "hause \u00f6konomie technik", "technische kaufm\u00e4nnischer kompetenz", "vertiefungsrichtung", "informationstechnik", "interesse", "wirtschaftsingenieurwesens themen ingenieurmathematik", "\u00fcbertragungstechnik systemtheorie", "stark technischem kontext", "inhalten vertiefungsrichtung", "voranschreitenden", "digitalisierungsprozess", "bedeutenden bet\u00e4tigungsfeld", "wirtschaftsingenieure fokussierung", "besonderen herausforderungen", "zunehmend verschmelzenden digitalen", "realenxawelt", "kern", "vertiefungsrichtung", "grundlagen data science", "g\u00fcterproduktion", "umfassende optimierung", "diagnose produktionssysteme", "wirtschaftsingenieure zuk\u00fcnftig verst\u00e4rkt erkenntnisse entwicklungen", "vertiefung", "w\u00fcnsche pr\u00e4ferenzen", "marketing", "marktorientierte unternehmensf\u00fchrung", "zentrum vertiefung", "technologischen gesellschaftlichen wandel", "weiterer fokus", "neuen medien", "bedeutung marketing", "marketingmix", "marketing medienmanagement dienstleistungsmanagement", "theoretisch praktisch erarbeitet fundiertes wissen", "marken", "diesexavertiefungsrichtung", "anforderungenxaan", "komplexer experten", "schwerpunkte", "informationsmanagement", "daher auseinandersetzung", "datenbanken officeanwendungen webtechnologien", "vertiefungsrichtung", "wirtschaftliche entwicklung", "letzten jahrzehnte", "komplexe globale unternehmensnetzwerke g\u00fcterstromsysteme", "gestalten", "betriebs", "gesichtspunkten", "fundierte kenntnisse f\u00e4higkeiten", "beschaffung", "produktion logistik", "schwerpunktthemen", "produktions", "beschaffungsmanagement inhalten wenden", "sieben dual", "praxisbl\u00f6cke vorlesungsphasen", "lernorte", "abxaw\u00e4hrend vorlesungszeit", "vollzeit", "pr\u00fcfungen vorlesungsfreien", "phasen", "theoretisches wissen", "schulen kompetenzen", "betriebliche abl\u00e4ufe", "praxiseins\u00e4tzen", "detaillierte dualen", "duales", "studienabg\u00e4nger genie\u00dfen hervorragenden ruf", "fach", "f\u00fchrungskr\u00e4fte", "absolventenstatistik", "rund prozent", "erhalt abschlusszeugnisse arbeitsvertrag", "wirtschaftsingenieure fachwissen f\u00e4higkeit", "schnittstelle technik wirtschaft", "exzellente jobchancen", "nahezu branchen unternehmensbereichen", "industrie handel dienstleistungssektor", "produktion", "marketing", "controlling beratung", "gesundheitsmanagement st\u00e4rker nachgefragt technischen vertrieb", "wirtschaftsingenieure produkte", "kunden", "bed\u00fcrfnisse", "kunden", "absprache", "arbeitsabl\u00e4ufe", "fertigungsauftr\u00e4ge", "lagerbest\u00e4nde betrieben", "produktion", "controlling", "ursachen", "wirtschaftlichkeit", "neuer produkte", "neuen gesch\u00e4ftsideen", "eigenexastartups", "workshops", "prozess professoren", "jungunternehmern", "rat", "bachelorabschluss", "f\u00fchrungsaufgaben wissenschaftliche karriere", "klima", "treten", "verbesserung", "insiderinfos", "berufspraxis", "wedeler hochschulbund zeichnet projektgruppen", "hochschulprozesse", "rechte", "daf\u00fcr verwendet auszuwerten", "eingaben eingegeben analysieren", "verwenden", "optimierungen", "llc", "erfassung", "benutzers", "nutzererlebnis", "drittanbieter", "client", "youtubenocookiecom", "buchstaben", "erm\u00f6glichen", "lokalen ger\u00e4t", "l\u00f6schen", "ausgelesen erm\u00f6glichen get\u00e4tigten", "besuchten ermitteln", "notwendige funktionsf\u00e4higkeit", "session", "analyse", "speichern", "besuche trafficquellen", "leistung", "n\u00fctzlichsten besucher", "navigieren fehlermeldungen", "l\u00e4ngeren ger\u00e4t", "gesammelten verbessern", "benutzerfreundlichkeit", "intuitivere navigation", "positiveres", "bachelor wirtschaftsingenieurwesen fh wedel bei hamburg"]}, {"stud_url": "https://www.fh-wedel.de/bewerben/bachelor/wirtschaftsinformatik/", "title": "Bachelor Wirtschaftsinformatik | FH Wedel bei Hamburg", "paragraphs": ["n\u00e4chste digitale", "halbst\u00fcndigen zoompr\u00e4sentation", "studieninhalten", "infosessions", "wirtschaftsinformatiker", "wirtschaftlicher prozesse", "informatik", "gegensatz", "informatik", "vordergrund programmiersprachen methoden softwareentwicklung", "wesentliche bestandteile", "wirtschaftlichen grundlagen", "betriebswirtschaftliche prozesse", "softwaresystemen", "praxisrelevanten kontext", "studentischen projekten", "realen problemstellungen", "weise", "enge kontakte", "industrie", "wirtschaft", "hamburger norddeutschen raumxaunternehmensvertreter", "vorlesungen", "workshops stellen themen", "regen", "wissenstransfer wirtschaft", "wirtschaftsinformatik", "vielseitige kooperationen", "starke kooperationen wirtschaft", "optimale verschaffen", "drittanbietercookies", "grundlagen informatik", "informatik", "wichtigsten programmiersprachen java java script fokus", "programmiersprachen", "umgang", "leichtfallen weiterf\u00fchrende konzepte programmierung plan", "darunter objektorientierte programmierung", "bestimmtes verfahren", "programme", "grundlagen", "logische formelsprache", "veranstaltungen", "datenbanken", "datenschutz", "themen", "logistik", "wirtschaftlichen aspekte zusammenspiel", "it wirtschaftlichen prozessen", "erpsystemen softwarel\u00f6sungen ressourcenplanung", "kenntnisse programms aris", "abl\u00e4ufe", "\u00fcbersichtliches modell", "schwachstellen", "aufdecken prozesse optimieren f\u00fcnften gehen vertiefungsrichtung", "informatik wirtschaft", "spezialisierung", "praxisorientierte guten kontakte", "ausreichendes handwerkszeug", "werkstudentent\u00e4tigkeit", "vorlesungsfreien", "siebten arbeiten", "betriebspraktikums", "verfassen", "bachelor", "science bsc", "vertiefen modulen informationstechnisches wissen", "basistechnologien k\u00fcnstlichen intelligenz", "implementierung", "methoden", "software", "softwaretests", "vertraut prozessmodellimplementation", "abgrenzung desktop", "kontext", "betrieblicher anwendungssysteme", "geeignete anwendungsszenarien", "vertiefungsrichtung", "wirtschaft", "praktischen anwendung", "wissens", "themen", "produktionsmanagement", "logistikmanagement dienstleistungsmanagement", "marketing", "wirtschaftliche einsatzbereiche informationstechnik", "wirtschaftsinformatik sieben dual", "praxisbl\u00f6cke vorlesungsphasen", "lernorte", "abxaw\u00e4hrend vorlesungszeit", "vollzeit", "pr\u00fcfungen vorlesungsfreien", "phasen", "theoretisches wissen", "schulen kompetenzen", "betriebliche abl\u00e4ufe", "praxiseins\u00e4tzen", "detaillierte dualen", "duales", "hoch engagierte dynamische fach", "absolventenstatistik", "rund prozent", "erhalt", "abschlusszeugnisse arbeitsvertrag", "softwareentwicklung", "unternehmensit", "unternehmensberatung", "wirtschaftsinformatiker", "effizienz", "sollkonzepte", "unternehmensspezifische softwarel\u00f6sungen", "entwickeln", "informations", "kommunikationssysteme", "systeme", "mitarbeiter", "software", "unterst\u00fctzt eigenexastartups", "workshops", "prozess professoren", "jungunternehmern", "rat", "bachelorabschluss", "f\u00fchrungsaufgaben wissenschaftliche karriere", "masterstudium", "wirtschaft", "klima", "pedale treten", "feedback", "verbesserung", "insiderinfos", "berufspraxis", "rechte", "vorbehalten", "daf\u00fcr verwendet auszuwerten", "eingaben eingegeben analysieren", "verwenden", "optimierungen", "llc", "erfassung", "benutzers", "nutzererlebnis", "drittanbieter", "client", "youtubenocookiecom", "buchstaben", "erm\u00f6glichen", "lokalen ger\u00e4t", "l\u00f6schen", "ausgelesen erm\u00f6glichen get\u00e4tigten", "besuchten ermitteln", "notwendige funktionsf\u00e4higkeit", "session", "analyse", "speichern", "besuche trafficquellen", "leistung", "n\u00fctzlichsten besucher", "navigieren fehlermeldungen", "l\u00e4ngeren ger\u00e4t", "gesammelten verbessern", "benutzerfreundlichkeit", "intuitivere navigation", "positiveres", "bachelor wirtschaftsinformatik fh wedel bei hamburg"]}, {"stud_url": "https://www.fh-wedel.de/bewerben/bachelor/technische-informatik/", "title": "Bachelor Technische Informatik | FH Wedel bei Hamburg", "paragraphs": ["n\u00e4chste digitale", "halbst\u00fcndigen zoompr\u00e4sentation", "studieninhalten", "infosessions", "informatikzweigen software", "besch\u00e4ftigtxasich technische informatikxasowohl software", "computern", "sp\u00fclmaschinen fahrzeugen", "mikrocomputer", "eingebettete systeme", "software zusammenspielen", "wer", "programmiertxaist", "richtigen", "klassische computersysteme", "esxafatal fahrzeug", "airbag", "ausxatechnische informatiker", "derartige kontext", "gesamtsystems", "zusammenspielenxatechnische informatiker", "spannungsversorgung", "redundante komponenten", "software verifizieren", "entsprechende zulassungsstellen", "breites wissensfundament", "realit\u00e4t", "konfrontierenxaunternehmensvertreter sindxain", "berufsalltag", "kooperierenxabereits", "m\u00f6glichkeit", "eigenes professionelles netzwerk", "werkstudent kooperationsunternehmen", "video", "drittanbietercookies", "technische informatik", "wesentlichen bestandteile", "computern", "digitalen", "systemen", "software", "grundlagen informatik", "elektronik", "digitaltechnik", "praxisnah", "soft", "c", "java programmieren", "steuerungs regelungs automatisierungstechnik", "lehrveranstaltungen physik", "\u00fcbertragungstechnik", "analogen", "digitalen schaltungsentwurfs", "stellen", "praktische produktentwicklung", "einfacher schneller handvoll", "einfacher elektronischer bauteile", "gro\u00dfen mikroprozessoren", "technischer informatiker", "aufgabe", "anforderung", "l\u00f6sungsvarianten", "theorie", "besondere aufgabenstellungen", "mitreden mitgestalten verh\u00e4ltnis", "professoren", "ausgesprochen pers\u00f6nlich freundschaftlich besonders ausreichendes handwerkszeug", "werkstudent", "praktikum", "vorlesungsfreien", "rahmen", "freiwilligen auslandssemesters", "betriebspraktikum", "berufserfahrung", "bachelor", "science bsc", "studienverlauf", "praxisbl\u00f6cke vorlesungsphasen", "lernorte", "abxaw\u00e4hrend vorlesungszeit", "vollzeit", "pr\u00fcfungen vorlesungsfreien", "phasen", "theoretisches wissen", "schulen kompetenzen", "betriebliche abl\u00e4ufe", "praxiseins\u00e4tzen", "detaillierte dualen", "duales", "dynamische", "f\u00fchrungskr\u00e4fte", "rund prozent", "bachelorabsolventen", "erhalt", "abschlusszeugnisse arbeitsvertrag", "technische informatiker", "fachwissen f\u00e4higkeit", "schnittstelle software", "anwendungsbranchen kommunikationstechnikxatelekommunikations energietechnik", "automobilindustriexaluft", "raumfahrt", "robotik industrietechnik", "medizintechnik", "sicherheit", "neuen gesch\u00e4ftsideen", "startups", "workshops", "prozess professoren", "jungunternehmern", "rat", "bachelorabschluss", "f\u00fchrungsaufgaben wissenschaftliche karriere", "schwerpunkt", "technik wissensmanagement", "klima", "treten", "verbesserung", "insiderinfos", "berufspraxis", "rechte", "vorbehalten", "daf\u00fcr verwendet auszuwerten", "eingaben eingegeben analysieren", "verwenden", "optimierungen", "llc", "erfassung", "benutzers", "nutzererlebnis", "drittanbieter", "client", "youtubenocookiecom", "buchstaben", "erm\u00f6glichen", "lokalen ger\u00e4t", "l\u00f6schen", "ausgelesen erm\u00f6glichen get\u00e4tigten", "besuchten ermitteln", "notwendige funktionsf\u00e4higkeit", "session", "analyse", "speichern", "besuche trafficquellen", "leistung", "n\u00fctzlichsten besucher", "navigieren fehlermeldungen", "l\u00e4ngeren ger\u00e4t", "gesammelten verbessern", "benutzerfreundlichkeit", "intuitivere navigation", "positiveres", "bachelor technische informatik fh wedel bei hamburg"]}, {"stud_url": "https://www.fh-wedel.de/bewerben/bachelor/betriebswirtschaftslehre/beirat-betriebswirtschaftslehre/", "title": "Beirat Betriebswirtschaftslehre | FH Wedel", "paragraphs": ["studienangebot", "intensiven austausch", "bachelor", "masterstudieng\u00e4ngen", "stetige anbindung", "praxisrelevanz", "berufseinstieg", "wirtschaftliche entwicklungen", "praxisvertreter", "l\u00f6sungen", "neuer relevanter", "innovative forschungsprojekte", "fallstudien", "initiiert mitglieder", "praxisbeitr\u00e4ge", "workshops", "rechte", "daf\u00fcr verwendet auszuwerten", "eingaben eingegeben analysieren", "verwenden", "optimierungen", "llc", "erfassung", "benutzers", "nutzererlebnis", "drittanbieter", "client", "youtubenocookiecom", "buchstaben", "erm\u00f6glichen", "lokalen ger\u00e4t", "l\u00f6schen", "ausgelesen erm\u00f6glichen get\u00e4tigten", "besuchten ermitteln", "notwendige funktionsf\u00e4higkeit", "session", "analyse", "speichern", "besuche trafficquellen", "leistung", "n\u00fctzlichsten besucher", "navigieren fehlermeldungen", "l\u00e4ngeren ger\u00e4t", "gesammelten verbessern", "benutzerfreundlichkeit", "intuitivere navigation", "positiveres", "beirat betriebswirtschaftslehre fh wedel"]}]